LICENSE
MANIFEST.in
README.md
setup.py
cicli/__init__.py
cicli/__main__.py
cicli/analyzers.py
cicli/app.py
cicli.egg-info/PKG-INFO
cicli.egg-info/SOURCES.txt
cicli.egg-info/dependency_links.txt
cicli.egg-info/entry_points.txt
cicli.egg-info/not-zip-safe
cicli.egg-info/requires.txt
cicli.egg-info/top_level.txt