Metadata-Version: 1.1
Name: cicli
Version: 0.1.0
Summary: CiCLI is a CircleCI command line tool.
Home-page: https://github.com/fastmonkeys/cicli
Author: Teemu Kokkonen, Raúl García
Author-email: teemu@fastmonkeys.com, pekka@fastmonkeys.com
License: BSD
Platform: any
Classifier: Intended Audience :: Developers
Classifier: License :: OSI Approved :: BSD License
Classifier: Operating System :: POSIX
Classifier: Operating System :: Microsoft :: Windows
Classifier: Operating System :: MacOS :: MacOS X
Classifier: Topic :: Utilities
Classifier: Programming Language :: Python :: 2
Classifier: Programming Language :: Python :: 3
Classifier: Topic :: Database
Classifier: Topic :: Software Development :: Version Control
